SyntheSys/__init__.py
SyntheSys/Analysis/Branch.py
SyntheSys/Analysis/Data.py
SyntheSys/Analysis/Module.py
SyntheSys/Analysis/Operation.py
SyntheSys/Analysis/Reduce.py
SyntheSys/Analysis/RessourceNode.py
SyntheSys/Analysis/Select.py
SyntheSys/Analysis/SelectGroup.py
SyntheSys/Analysis/SkipLines.py
SyntheSys/Analysis/Switch.py
SyntheSys/Analysis/SyntheSys_Algorithm.py
SyntheSys/Analysis/SyntheSys_Testbench.py
SyntheSys/Analysis/TBValues.py
SyntheSys/Analysis/TestGroup.py
SyntheSys/Analysis/Tracer.py
SyntheSys/Analysis/__init__.py
SyntheSys/Analysis/Misc/Misc.py
SyntheSys/Analysis/Misc/__init__.py
SyntheSys/Library/__init__.py
SyntheSys/Library/HDL/module.dtd
SyntheSys/Library/HDL/service.dtd
SyntheSys/Library/HDL/Management/Utilities.vhd
SyntheSys/Library/HDL/Management/Communication/Ethernet/IP_Ethernet.zip
SyntheSys/Library/HDL/Management/Communication/HERMES_NoC/HERMES_NOC.vhd
SyntheSys/Library/HDL/Management/Communication/HERMES_NoC/Hermes_buffer.vhd
SyntheSys/Library/HDL/Management/Communication/HERMES_NoC/Hermes_mux.vhd
SyntheSys/Library/HDL/Management/Communication/HERMES_NoC/Hermes_package.vhd
SyntheSys/Library/HDL/Management/Communication/HERMES_NoC/Hermes_switchcontrol.vhd
SyntheSys/Library/HDL/Management/Communication/HERMES_NoC/MUX.vhdl
SyntheSys/Library/HDL/Management/Communication/HERMES_NoC/NOC.vhd
SyntheSys/Library/HDL/Management/Communication/HERMES_NoC/RouterCC.vhd
SyntheSys/Library/HDL/Management/Communication/Misc/InterfaceAdapter/FifoToHandShake/FifoToHandShake.vhd
SyntheSys/Library/HDL/Management/Communication/Misc/InterfaceAdapter/FifoToHandShake/FifoToHandShake_simu.do
SyntheSys/Library/HDL/Management/Communication/Misc/InterfaceAdapter/FifoToHandShake/FifoToHandShake_tb.vhd
SyntheSys/Library/HDL/Management/Communication/Misc/InterfaceAdapter/FifoToHandShake/FifoToHandShake_tb_io.txt
SyntheSys/Library/HDL/Management/Communication/Misc/InterfaceAdapter/FifoToHandShake/FileList.txt
SyntheSys-0.1.2.dist-info/METADATA
SyntheSys-0.1.2.dist-info/RECORD
SyntheSys-0.1.2.dist-info/WHEEL
SyntheSys-0.1.2.dist-info/top_level.txt
